<annotation verified="no">
  <folder>long</folder>
  <filename>0676</filename>
  <path>/opt/Deep_Learning_Data/Insulator/long/0676.jpg</path>
  <source>
    <database>Unknown</database>
  </source>
  <size>
    <width>1152</width>
    <height>864</height>
    <depth>3</depth>
  </size>
  <segmented>0</segmented>
  <object>
    <name>insulator</name>
    <pose>Unspecified</pose>
    <truncated>0</truncated>
    <difficult>0</difficult>
    <bndbox>
      <xmin>169</xmin>
      <ymin>369</ymin>
      <xmax>1059</xmax>
      <ymax>549</ymax>
    </bndbox>
  </object>
  <object>
    <name>insulator</name>
    <pose>Unspecified</pose>
    <truncated>0</truncated>
    <difficult>0</difficult>
    <bndbox>
      <xmin>235</xmin>
      <ymin>83</ymin>
      <xmax>584</xmax>
      <ymax>158</ymax>
    </bndbox>
  </object>
</annotation>
